.DS_Store
.gitignore
.readthedocs.yaml
CONTRIBUTING.md
LICENSE
Makefile
README.md
__init__.py
codecov.yml
pyproject.toml
requirements.txt
setup.py
.github/dependabot.yml
.github/ISSUE_TEMPLATE/bug_report.md
.github/ISSUE_TEMPLATE/feature_request.md
.github/workflows/workflow.yml
docs/.DS_Store
docs/Makefile
docs/conf.py
docs/index.rst
docs/make.bat
docs/requirements.txt
docs/transfer-all.gif
docs/transfer-single.gif
src/__init__.py
src/apple_private_key.p8
src/spotify_client.py
src/spotify_to_apple_py.egg-info/PKG-INFO
src/spotify_to_apple_py.egg-info/SOURCES.txt
src/spotify_to_apple_py.egg-info/dependency_links.txt
src/spotify_to_apple_py.egg-info/requires.txt
src/spotify_to_apple_py.egg-info/top_level.txt
tests/__init__.py
tests/sample_apple_private_key.p8
tests/tests.py