Metadata-Version: 2.1
Name: spotify-to-apple-py
Version: 0.2.1
Summary: Convert spotify playlists to apple music
Home-page: https://github.com/Beza4598/spotify_apple_converter.git
Author: Beza Amsalu
Author-email: Beza Amsalu <beza.amsalu@columbia.edu>
License: MIT License
Project-URL: repository, https://github.com/columbiaoss/example-project-python
Classifier: Development Status :: 2 - Pre-Alpha
Classifier: Programming Language :: Python :: Implementation :: CPython
Classifier: Programming Language :: Python :: Implementation :: PyPy
Classifier: Programming Language :: Python :: 3
Classifier: Programming Language :: Python :: 3.7
Classifier: Programming Language :: Python :: 3.8
Classifier: Programming Language :: Python :: 3.9
Classifier: Programming Language :: Python :: 3.10
Classifier: Programming Language :: Python :: 3.11
Requires-Python: >=3.7
Provides-Extra: develop
License-File: LICENSE
